AUTHORS.rst
CONTRIBUTING.rst
HISTORY.rst
LICENSE
MANIFEST.in
README.rst
setup.py
complexity/__init__.py
complexity/conf.py
complexity/exceptions.py
complexity/generate.py
complexity/main.py
complexity/prep.py
complexity/serve.py
complexity/utils.py
complexity.egg-info/PKG-INFO
complexity.egg-info/SOURCES.txt
complexity.egg-info/dependency_links.txt
complexity.egg-info/entry_points.txt
complexity.egg-info/not-zip-safe
complexity.egg-info/requires.txt
complexity.egg-info/top_level.txt