Metadata-Version: 1.1
Name: complexity
Version: 0.7
Summary: A refreshingly simple static site generator, for those who like to work in HTML.
Home-page: https://github.com/audreyr/complexity
Author: Audrey Roy
Author-email: audreyr@gmail.com
License: BSD
Keywords: complexity,static site generator,HTML,Jinja2,templates,S3
Platform: UNKNOWN
Classifier: Development Status :: 2 - Pre-Alpha
Classifier: Environment :: Console
Classifier: Intended Audience :: Developers
Classifier: License :: OSI Approved :: BSD License
Classifier: Natural Language :: English
Classifier: Programming Language :: Python :: 2.6
Classifier: Programming Language :: Python :: 2.7
Classifier: Programming Language :: Python :: 3.3
Classifier: Topic :: Internet :: WWW/HTTP :: Site Management
